genlib/__init__.py
genlib/ansiec.py
genlib/hdlc.py
genlib/ican.py
genlib/slip.py
genlib/udp.py
genlib-0.6.1.dist-info/LICENSE
genlib-0.6.1.dist-info/METADATA
genlib-0.6.1.dist-info/WHEEL
genlib-0.6.1.dist-info/top_level.txt
genlib-0.6.1.dist-info/RECORD
