Metadata-Version: 2.2
Name: genlib
Version: 0.6.1
Summary: This is the basic library for xkit.
Home-page: https://github.com/planxstudio/genlib
Author: chanmin.park
Author-email: devcamp@gmail.com
Keywords: embedded,upyboard,pyserial
Classifier: Programming Language :: Python :: 3
Classifier: License :: OSI Approved :: MIT License
Classifier: Operating System :: OS Independent
Requires-Python: >=3.8
License-File: LICENSE
Requires-Dist: ifaddr
Dynamic: author
Dynamic: author-email
Dynamic: classifier
Dynamic: description
Dynamic: description-content-type
Dynamic: home-page
Dynamic: keywords
Dynamic: requires-dist
Dynamic: requires-python
Dynamic: summary
